analytics/__init__.py
analytics/cycles.py
analytics/main.py
dep_graph_analytics-1.0.3.dist-info/METADATA
dep_graph_analytics-1.0.3.dist-info/WHEEL
dep_graph_analytics-1.0.3.dist-info/entry_points.txt
dep_graph_analytics-1.0.3.dist-info/namespace_packages.txt
dep_graph_analytics-1.0.3.dist-info/top_level.txt
dep_graph_analytics-1.0.3.dist-info/RECORD
