Metadata-Version: 2.1
Name: dep-graph-analytics
Version: 1.0.3
Summary: A toolset to query codebase dependency graph data using networkx.
Requires-Python: >=3.9
Requires-Dist: fire
Requires-Dist: networkx
